commonutil_fileio_checksum/__init__.py
commonutil_fileio_checksum/py.typed
commonutil_fileio_checksum-3.1.0.dist-info/METADATA
commonutil_fileio_checksum-3.1.0.dist-info/WHEEL
commonutil_fileio_checksum-3.1.0.dist-info/top_level.txt
commonutil_fileio_checksum-3.1.0.dist-info/RECORD
